{
 "space": "plate world units (wu); 1 wu = 0.25 m; plate 1800x1000 wu = 450x250 m",
 "transform": {
  "m_per_wu": 0.25,
  "wu_per_px": 0.878906,
  "origin_wu": [
   900,
   100
  ],
  "note": "bible = right half of plate; uniform linear map"
 },
 "nav_paths": [
  {
   "id": "p2",
   "type": "street",
   "pts": [
    [
     1797.36,
     519.24
    ],
    [
     1601.37,
     518.36
    ],
    [
     1589.06,
     505.18
    ],
    [
     1594.34,
     470.02
    ],
    [
     1582.91,
     448.05
    ],
    [
     1542.48,
     430.47
    ],
    [
     1495.02,
     419.92
    ],
    [
     1473.93,
     422.56
    ],
    [
     1440.53,
     446.29
    ],
    [
     1417.68,
     469.14
    ],
    [
     1411.52,
     493.75
    ],
    [
     1423.83,
     518.36
    ],
    [
     1451.07,
     534.18
    ],
    [
     1476.56,
     541.21
    ],
    [
     1509.96,
     542.97
    ],
    [
     1533.69,
     541.21
    ],
    [
     1560.06,
     535.94
    ],
    [
     1596.09,
     513.09
    ]
   ]
  },
  {
   "id": "p3",
   "type": "path",
   "pts": [
    [
     1478.32,
     560.55
    ],
    [
     1467.77,
     555.27
    ],
    [
     1442.29,
     545.61
    ],
    [
     1413.28,
     530.66
    ],
    [
     1411.52,
     530.66
    ],
    [
     1396.58,
     529.79
    ],
    [
     1375.49,
     540.33
    ],
    [
     1360.55,
     545.61
    ],
    [
     1332.42,
     556.15
    ],
    [
     1313.96,
     571.97
    ],
    [
     1293.75,
     592.19
    ],
    [
     1277.93,
     610.64
    ],
    [
     1258.59,
     630.86
    ],
    [
     1256.84,
     644.04
    ],
    [
     1293.75,
     655.47
    ],
    [
     1328.03,
     663.38
    ],
    [
     1360.55,
     665.14
    ],
    [
     1367.58,
     664.26
    ],
    [
     1377.25,
     663.38
    ],
    [
     1388.67,
     645.8
    ],
    [
     1405.37,
     623.83
    ],
    [
     1431.74,
     600.1
    ],
    [
     1461.62,
     578.12
    ],
    [
     1482.71,
     561.43
    ],
    [
     1516.99,
     556.15
    ],
    [
     1534.57,
     551.76
    ],
    [
     1562.7,
     543.85
    ],
    [
     1596.09,
     513.09
    ],
    [
     1600.49,
     508.69
    ],
    [
     1615.43,
     488.48
    ],
    [
     1606.64,
     460.35
    ],
    [
     1593.46,
     442.77
    ],
    [
     1552.15,
     422.56
    ],
    [
     1479.2,
     407.62
    ],
    [
     1443.16,
     426.07
    ],
    [
     1400.1,
     461.23
    ],
    [
     1386.91,
     481.45
    ],
    [
     1384.28,
     497.27
    ],
    [
     1394.82,
     518.36
    ],
    [
     1411.52,
     530.66
    ]
   ]
  },
  {
   "id": "p5",
   "type": "path",
   "pts": [
    [
     1255.08,
     643.16
    ],
    [
     1112.7,
     724.9
    ],
    [
     1090.72,
     715.23
    ],
    [
     1041.5,
     658.98
    ],
    [
     1007.23,
     615.04
    ],
    [
     1002.83,
     575.49
    ],
    [
     1007.23,
     554.39
    ],
    [
     1031.84,
     515.72
    ],
    [
     1049.41,
     494.63
    ],
    [
     1088.96,
     477.05
    ],
    [
     1108.3,
     462.99
    ],
    [
     1110.06,
     461.23
    ]
   ]
  },
  {
   "id": "p6",
   "type": "path",
   "pts": [
    [
     1255.08,
     643.16
    ],
    [
     1288.48,
     678.32
    ],
    [
     1287.6,
     690.62
    ],
    [
     1269.14,
     702.05
    ],
    [
     1250.68,
     716.11
    ],
    [
     1223.44,
     734.57
    ],
    [
     1189.16,
     753.91
    ],
    [
     1147.85,
     776.76
    ],
    [
     1109.18,
     786.43
    ],
    [
     1075.78,
     781.15
    ],
    [
     1044.14,
     764.45
    ],
    [
     1016.02,
     738.96
    ],
    [
     1002.83,
     721.39
    ],
    [
     971.19,
     665.14
    ],
    [
     955.37,
     637.89
    ],
    [
     951.86,
     617.68
    ],
    [
     953.61,
     555.27
    ],
    [
     987.01,
     502.54
    ],
    [
     1037.99,
     468.26
    ],
    [
     1107.42,
     452.44
    ],
    [
     1111.82,
     449.8
    ],
    [
     1127.64,
     453.32
    ],
    [
     1132.03,
     454.2
    ],
    [
     1127.64,
     455.96
    ],
    [
     1108.3,
     462.99
    ]
   ]
  },
  {
   "id": "p8",
   "type": "path",
   "pts": [
    [
     1328.03,
     664.26
    ],
    [
     1350.88,
     681.84
    ],
    [
     1359.67,
     703.81
    ],
    [
     1360.55,
     731.93
    ],
    [
     1347.36,
     758.3
    ],
    [
     1321.0,
     789.06
    ],
    [
     1248.93,
     833.01
    ],
    [
     1150.49,
     881.35
    ],
    [
     1077.54,
     895.41
    ],
    [
     1001.95,
     860.25
    ],
    [
     953.61,
     826.86
    ],
    [
     910.55,
     777.64
    ],
    [
     907.91,
     772.36
    ],
    [
     899.12,
     757.42
    ]
   ]
  },
  {
   "id": "p9",
   "type": "path",
   "pts": [
    [
     1567.09,
     592.19
    ],
    [
     1558.3,
     610.64
    ],
    [
     1563.57,
     632.62
    ],
    [
     1562.7,
     646.68
    ],
    [
     1560.06,
     661.62
    ],
    [
     1566.21,
     672.17
    ],
    [
     1632.13,
     696.78
    ],
    [
     1654.1,
     710.84
    ],
    [
     1660.25,
     713.48
    ],
    [
     1663.77,
     715.23
    ],
    [
     1672.56,
     707.32
    ],
    [
     1680.47,
     700.29
    ],
    [
     1688.38,
     693.26
    ]
   ]
  },
  {
   "id": "p10",
   "type": "path",
   "pts": [
    [
     1660.25,
     713.48
    ],
    [
     1640.92,
     729.3
    ],
    [
     1619.82,
     728.42
    ],
    [
     1605.76,
     719.63
    ],
    [
     1560.06,
     691.5
    ]
   ]
  },
  {
   "id": "p11",
   "type": "path",
   "pts": [
    [
     1641.8,
     728.42
    ],
    [
     1662.89,
     751.27
    ],
    [
     1679.59,
     760.06
    ],
    [
     1678.71,
     758.3
    ],
    [
     1642.68,
     789.94
    ],
    [
     1618.95,
     810.16
    ],
    [
     1644.43,
     832.13
    ],
    [
     1702.44,
     859.38
    ],
    [
     1729.69,
     839.16
    ],
    [
     1730.57,
     823.34
    ],
    [
     1683.11,
     800.49
    ]
   ]
  },
  {
   "id": "p13",
   "type": "path",
   "pts": [
    [
     1672.56,
     707.32
    ],
    [
     1731.45,
     736.33
    ]
   ]
  },
  {
   "id": "p15",
   "type": "path",
   "pts": [
    [
     1127.64,
     455.96
    ],
    [
     1258.59,
     471.78
    ],
    [
     1277.05,
     462.11
    ],
    [
     1284.96,
     447.17
    ],
    [
     1289.36,
     433.98
    ],
    [
     1272.66,
     430.47
    ],
    [
     1261.23,
     423.44
    ],
    [
     1249.8,
     422.56
    ],
    [
     1270.9,
     408.5
    ],
    [
     1317.48,
     389.16
    ],
    [
     1333.3,
     375.98
    ],
    [
     1355.27,
     365.43
    ],
    [
     1371.97,
     349.61
    ],
    [
     1351.76,
     343.46
    ],
    [
     1333.3,
     340.82
    ],
    [
     1304.3,
     334.67
    ],
    [
     1289.36,
     329.39
    ],
    [
     1280.57,
     320.61
    ],
    [
     1308.69,
     306.54
    ],
    [
     1342.09,
     288.96
    ],
    [
     1376.37,
     274.02
    ],
    [
     1407.13,
     258.2
    ],
    [
     1425.59,
     242.38
    ],
    [
     1364.94,
     225.68
    ],
    [
     1343.85,
     216.02
    ]
   ]
  },
  {
   "id": "p16",
   "type": "path",
   "pts": [
    [
     1280.57,
     320.61
    ],
    [
     1257.71,
     315.33
    ],
    [
     1204.98,
     348.73
    ],
    [
     1125.0,
     317.09
    ],
    [
     1096.0,
     327.64
    ],
    [
     1080.18,
     325.88
    ],
    [
     1074.9,
     320.61
    ],
    [
     1075.78,
     310.94
    ],
    [
     1080.18,
     303.91
    ],
    [
     1089.84,
     295.12
    ],
    [
     1093.36,
     290.72
    ],
    [
     1107.42,
     281.93
    ],
    [
     1148.73,
     283.69
    ],
    [
     1155.76,
     277.54
    ],
    [
     1156.64,
     265.23
    ],
    [
     1156.64,
     257.32
    ],
    [
     1137.3,
     242.38
    ],
    [
     1157.52,
     231.84
    ],
    [
     1143.46,
     230.96
    ],
    [
     1093.36,
     245.02
    ],
    [
     1036.23,
     268.75
    ],
    [
     983.5,
     288.96
    ],
    [
     948.34,
     305.66
    ],
    [
     941.31,
     322.36
    ]
   ]
  },
  {
   "id": "p18",
   "type": "path",
   "pts": [
    [
     1478.32,
     408.5
    ],
    [
     1469.53,
     390.92
    ],
    [
     1505.57,
     355.76
    ],
    [
     1583.79,
     368.95
    ],
    [
     1641.8,
     382.13
    ],
    [
     1676.95,
     390.04
    ],
    [
     1693.65,
     354.0
    ],
    [
     1699.8,
     340.82
    ],
    [
     1702.44,
     332.03
    ],
    [
     1789.45,
     345.21
    ]
   ]
  },
  {
   "id": "p19",
   "type": "path",
   "pts": [
    [
     1705.96,
     332.03
    ],
    [
     1505.57,
     294.24
    ]
   ]
  },
  {
   "id": "p20",
   "type": "lane",
   "pts": [
    [
     1367.58,
     664.26
    ],
    [
     1378.12,
     716.11
    ],
    [
     1374.61,
     738.09
    ],
    [
     1361.43,
     775.88
    ],
    [
     1328.91,
     804.0
    ],
    [
     1279.69,
     840.04
    ],
    [
     1207.62,
     877.83
    ],
    [
     1135.55,
     902.44
    ],
    [
     1062.6,
     905.96
    ],
    [
     991.41,
     881.35
    ],
    [
     949.22,
     851.46
    ],
    [
     911.43,
     805.76
    ],
    [
     907.91,
     772.36
    ]
   ]
  },
  {
   "id": "p21",
   "type": "lane",
   "pts": [
    [
     1208.5,
     708.2
    ],
    [
     1117.09,
     745.12
    ],
    [
     1049.41,
     719.63
    ],
    [
     995.8,
     653.71
    ],
    [
     975.59,
     588.67
    ],
    [
     1002.83,
     520.12
    ],
    [
     1037.99,
     489.36
    ],
    [
     1075.78,
     470.9
    ],
    [
     1110.06,
     461.23
    ],
    [
     1117.97,
     459.47
    ],
    [
     1127.64,
     453.32
    ]
   ]
  },
  {
   "id": "p22",
   "type": "river",
   "pts": [
    [
     1542.48,
     586.04
    ],
    [
     1496.78,
     609.77
    ],
    [
     1473.05,
     653.71
    ],
    [
     1464.26,
     693.26
    ],
    [
     1468.65,
     723.14
    ],
    [
     1489.75,
     753.91
    ],
    [
     1510.84,
     796.09
    ],
    [
     1521.39,
     831.25
    ],
    [
     1524.02,
     853.22
    ],
    [
     1508.2,
     883.98
    ],
    [
     1482.71,
     927.93
    ],
    [
     1446.68,
     952.54
    ],
    [
     1402.73,
     982.42
    ],
    [
     1370.21,
     996.48
    ]
   ]
  },
  {
   "id": "oak_spur",
   "type": "path",
   "pts": [
    [
     1702.44,
     859.38
    ],
    [
     1727.93,
     945.51
    ]
   ]
  },
  {
   "id": "p1003",
   "type": "street",
   "pts": [
    [
     1656.74,
     545.61
    ],
    [
     1601.37,
     518.36
    ]
   ]
  }
 ],
 "connectors": [
  {
   "id": "door_2",
   "type": "door",
   "place": 2,
   "pts": [
    [
     1481.84,
     449.8
    ],
    [
     1466.02,
     427.83
    ]
   ]
  },
  {
   "id": "door_5",
   "type": "door",
   "place": 5,
   "pts": [
    [
     1636.52,
     407.62
    ],
    [
     1641.8,
     382.13
    ]
   ]
  },
  {
   "id": "door_6",
   "type": "door",
   "place": 6,
   "pts": [
    [
     1666.41,
     486.72
    ],
    [
     1666.41,
     518.36
    ]
   ]
  },
  {
   "id": "door_8",
   "type": "door",
   "place": 8,
   "pts": [
    [
     1053.81,
     225.68
    ],
    [
     1066.11,
     256.45
    ]
   ]
  },
  {
   "id": "door_9",
   "type": "door",
   "place": 9,
   "pts": [
    [
     957.13,
     266.99
    ],
    [
     970.31,
     295.12
    ]
   ]
  },
  {
   "id": "door_10",
   "type": "door",
   "place": 10,
   "pts": [
    [
     1418.55,
     398.83
    ],
    [
     1441.41,
     426.95
    ]
   ]
  },
  {
   "id": "door_13",
   "type": "door",
   "place": 13,
   "pts": [
    [
     1040.62,
     810.16
    ],
    [
     1059.96,
     773.24
    ]
   ]
  },
  {
   "id": "door_14",
   "type": "door",
   "place": 14,
   "pts": [
    [
     1106.54,
     936.72
    ],
    [
     1104.79,
     904.2
    ]
   ]
  },
  {
   "id": "door_16",
   "type": "door",
   "place": 16,
   "pts": [
    [
     1198.83,
     324.12
    ],
    [
     1190.92,
     343.46
    ]
   ]
  },
  {
   "id": "door_17",
   "type": "door",
   "place": 17,
   "pts": [
    [
     1374.61,
     640.53
    ],
    [
     1386.91,
     648.44
    ]
   ]
  },
  {
   "id": "door_20",
   "type": "door",
   "place": 20,
   "pts": [
    [
     1110.94,
     637.89
    ],
    [
     1060.84,
     681.84
    ]
   ]
  }
 ],
 "dressing_paths": [
  {
   "id": "railway",
   "type": "rail",
   "pts": [
    [
     900.0,
     310.94
    ],
    [
     952.73,
     297.75
    ],
    [
     1014.26,
     280.18
    ],
    [
     1075.78,
     260.84
    ],
    [
     1146.09,
     238.87
    ],
    [
     1216.41,
     218.65
    ],
    [
     1286.72,
     201.95
    ],
    [
     1357.03,
     187.89
    ],
    [
     1418.55,
     180.86
    ]
   ],
   "circle": null
  },
  {
   "id": "high_street",
   "type": "street",
   "pts": [
    [
     1163.67,
     306.54
    ],
    [
     1216.41,
     330.27
    ],
    [
     1277.93,
     354.88
    ],
    [
     1339.45,
     376.86
    ],
    [
     1392.19,
     394.43
    ],
    [
     1444.92,
     409.38
    ],
    [
     1480.08,
     423.44
    ]
   ],
   "circle": null
  },
  {
   "id": "square_ring",
   "type": "street",
   "pts": null,
   "circle": {
    "c": [
     1515.23,
     469.14
    ],
    "rx": 75.59,
    "ry": 58.01
   }
  },
  {
   "id": "bridge_way",
   "type": "street",
   "pts": [
    [
     1554.79,
     520.12
    ],
    [
     1534.57,
     543.85
    ],
    [
     1515.23,
     561.43
    ]
   ],
   "circle": null
  },
  {
   "id": "riverside_street",
   "type": "street",
   "pts": [
    [
     1466.89,
     552.64
    ],
    [
     1425.59,
     581.64
    ],
    [
     1356.15,
     623.83
    ],
    [
     1287.6,
     673.05
    ],
    [
     1225.2,
     728.42
    ],
    [
     1169.82,
     789.94
    ],
    [
     1128.52,
     852.34
    ],
    [
     1095.12,
     914.75
    ],
    [
     1077.54,
     968.36
    ]
   ],
   "circle": null
  },
  {
   "id": "matchday_way",
   "type": "street",
   "pts": [
    [
     1583.79,
     506.05
    ],
    [
     1629.49,
     526.27
    ],
    [
     1657.62,
     541.21
    ]
   ],
   "circle": null
  },
  {
   "id": "north_lane",
   "type": "lane",
   "pts": [
    [
     1560.94,
     409.38
    ],
    [
     1608.4,
     386.52
    ],
    [
     1657.62,
     368.95
    ],
    [
     1706.84,
     356.64
    ]
   ],
   "circle": null
  },
  {
   "id": "allotment_lane",
   "type": "lane",
   "pts": [
    [
     998.44,
     506.05
    ],
    [
     1031.84,
     574.61
    ],
    [
     1080.18,
     640.53
    ],
    [
     1124.12,
     706.45
    ],
    [
     1163.67,
     769.73
    ],
    [
     1198.83,
     833.89
    ],
    [
     1232.23,
     891.02
    ],
    [
     1251.56,
     939.36
    ]
   ],
   "circle": null
  },
  {
   "id": "slate_spur",
   "type": "lane",
   "pts": [
    [
     1080.18,
     640.53
    ],
    [
     1031.84,
     671.29
    ],
    [
     992.29,
     697.66
    ]
   ],
   "circle": null
  },
  {
   "id": "river",
   "type": "river",
   "pts": [
    [
     1420.31,
     989.45
    ],
    [
     1427.34,
     908.59
    ],
    [
     1437.89,
     833.89
    ],
    [
     1450.2,
     757.42
    ],
    [
     1464.26,
     687.11
    ],
    [
     1481.84,
     622.95
    ],
    [
     1495.9,
     579.0
    ]
   ],
   "circle": null
  },
  {
   "id": "park_path_a",
   "type": "park",
   "pts": [
    [
     1657.62,
     541.21
    ],
    [
     1643.55,
     600.98
    ],
    [
     1625.98,
     662.5
    ],
    [
     1610.16,
     725.78
    ],
    [
     1599.61,
     794.34
    ]
   ],
   "circle": null
  },
  {
   "id": "park_path_b",
   "type": "park",
   "pts": [
    [
     1741.99,
     588.67
    ],
    [
     1717.38,
     662.5
    ],
    [
     1695.41,
     732.81
    ],
    [
     1699.8,
     810.16
    ],
    [
     1722.66,
     873.44
    ],
    [
     1726.17,
     921.78
    ]
   ],
   "circle": null
  },
  {
   "id": "park_path_c",
   "type": "park",
   "pts": [
    [
     1516.99,
     579.0
    ],
    [
     1531.05,
     627.34
    ],
    [
     1545.12,
     680.08
    ],
    [
     1555.66,
     732.81
    ]
   ],
   "circle": null
  }
 ],
 "crossings": [
  {
   "id": "xw_bridge",
   "on": "bridge_way",
   "world": [
    1525.78,
    550.0
   ]
  },
  {
   "id": "xw_matchday",
   "on": "matchday_way",
   "world": [
    1598.73,
    518.36
   ]
  }
 ],
 "places": [
  {
   "n": 1,
   "name": "Clock Tower",
   "role": "dressing",
   "world": [
    1525.78,
    418.16
   ]
  },
  {
   "n": 2,
   "name": "The Square Caf\u00e9",
   "role": "sim:loc_cafe",
   "world": [
    1481.84,
    449.8
   ]
  },
  {
   "n": 3,
   "name": "The Turnstile Arms",
   "role": "sim:loc_pub",
   "world": [
    1603.12,
    499.9
   ]
  },
  {
   "n": 4,
   "name": "Bakery",
   "role": "sim:loc_bakery",
   "world": [
    1343.85,
    379.49
   ]
  },
  {
   "n": 5,
   "name": "Museum",
   "role": "sim:loc_museum",
   "world": [
    1636.52,
    407.62
   ]
  },
  {
   "n": 6,
   "name": "Club Offices \u2014 ERA FC",
   "role": "system:new",
   "world": [
    1666.41,
    486.72
   ]
  },
  {
   "n": 7,
   "name": "Club Shop",
   "role": "system:new",
   "world": [
    1638.28,
    516.6
   ]
  },
  {
   "n": 8,
   "name": "Train Station",
   "role": "dressing",
   "world": [
    1053.81,
    225.68
   ]
  },
  {
   "n": 9,
   "name": "Stationmaster's House",
   "role": "named home",
   "world": [
    957.13,
    266.99
   ]
  },
  {
   "n": 10,
   "name": "Corner Grocer",
   "role": "shop:new",
   "world": [
    1418.55,
    398.83
   ]
  },
  {
   "n": 11,
   "name": "North Gate (ground plaza)",
   "role": "sim:loc_north_gate",
   "world": [
    1657.62,
    544.73
   ]
  },
  {
   "n": 12,
   "name": "Old Oak \u2014 Oakside",
   "role": "sim:loc_oakside",
   "world": [
    1727.93,
    945.51
   ]
  },
  {
   "n": 13,
   "name": "The Slate House",
   "role": "named home",
   "world": [
    1040.62,
    810.16
   ]
  },
  {
   "n": 14,
   "name": "Miller's Row",
   "role": "sim:loc_millers_row",
   "world": [
    1106.54,
    936.72
   ]
  },
  {
   "n": 15,
   "name": "Kiln Yard",
   "role": "sim:loc_kiln_yard",
   "world": [
    1121.48,
    720.51
   ]
  },
  {
   "n": 16,
   "name": "Elm Row",
   "role": "sim:loc_elm_row",
   "world": [
    1198.83,
    324.12
   ]
  },
  {
   "n": 17,
   "name": "Riverside Row",
   "role": "sim:loc_riverside",
   "world": [
    1374.61,
    640.53
   ]
  },
  {
   "n": 18,
   "name": "Old Bridge",
   "role": "sim:loc_bridge",
   "world": [
    1506.45,
    564.06
   ]
  },
  {
   "n": 19,
   "name": "The Ground",
   "role": "sim:loc_stadium",
   "world": [
    1726.17,
    588.67
   ]
  },
  {
   "n": 20,
   "name": "Allotments",
   "role": "dressing/future-sim",
   "world": [
    1110.94,
    637.89
   ]
  }
 ],
 "off_frame": {
  "loc_training_ground": {
   "world": [
    180,
    300
   ],
   "note": "far-left & back, behind the station (pitch+pavilion)"
  },
  "loc_school": {
   "world": [
    430,
    240
   ],
   "note": "left extension, back band"
  },
  "loc_weavers_lane": {
   "world": [
    470,
    720
   ],
   "note": "left extension, mid/low"
  },
  "loc_orchard_close": {
   "world": [
    1660,
    260
   ],
   "note": "behind NE terraces (right side)"
  },
  "loc_canal_side": {
   "world": [
    1650,
    520
   ],
   "note": "canal spur off the river (right side)"
  }
 },
 "sim_bindings": {
  "loc_stadium": [
   1726.17,
   588.67
  ],
  "loc_museum": [
   1636.52,
   407.62
  ],
  "loc_bakery": [
   1343.85,
   379.49
  ],
  "loc_main_square": [
   1515.23,
   469.14
  ],
  "loc_cafe": [
   1481.84,
   449.8
  ],
  "loc_pub": [
   1603.12,
   499.9
  ],
  "loc_bridge": [
   1506.45,
   564.06
  ],
  "loc_riverside": [
   1374.61,
   640.53
  ],
  "loc_millers_row": [
   1106.54,
   936.72
  ],
  "loc_high_street": [
   1339.45,
   376.86
  ],
  "loc_oakside": [
   1727.93,
   945.51
  ],
  "loc_elm_row": [
   1198.83,
   324.12
  ],
  "loc_kiln_yard": [
   1121.48,
   720.51
  ],
  "loc_north_gate": [
   1657.62,
   544.73
  ],
  "loc_club_offices": [
   1666.41,
   486.72
  ],
  "loc_club_shop": [
   1638.28,
   516.6
  ],
  "loc_corner_grocer": [
   1418.55,
   398.83
  ],
  "loc_school": [
   430,
   240
  ],
  "loc_weavers_lane": [
   470,
   720
  ],
  "loc_orchard_close": [
   1660,
   260
  ],
  "loc_canal_side": [
   1650,
   520
  ],
  "loc_training_ground": [
   180,
   300
  ]
 },
 "reconcile": [
  "bible #11 North Gate = the GROUND PLAZA, but sim loc_north_gate is currently a residential HOME.",
  "bible #3 pub = 'The Turnstile Arms', but current sim name is 'The Anchor'.",
  "off_frame + loc_main_square/high_street coords are PROVISIONAL \u2014 retune when the plate camera is locked (step 3)."
 ]
}